simpleloggerplus/__init__.py
simpleloggerplus/deepops.py
simpleloggerplus/simpleloggerplus.py
simpleloggerplus-0.0.4.post5.dist-info/LICENCE
simpleloggerplus-0.0.4.post5.dist-info/METADATA
simpleloggerplus-0.0.4.post5.dist-info/WHEEL
simpleloggerplus-0.0.4.post5.dist-info/top_level.txt
simpleloggerplus-0.0.4.post5.dist-info/RECORD
